[
    {
        "created": "20150215045550714",
        "title": "Tyranid Warriors",
        "text": "!!{{!!caption}} --- {{!!points}} points\n\n[[Infantry]]\n\n{{||CharacteristicsTable}}\n\n''Unit Composition'': 3 {{!!title}}\n\n{{||$:/templates/biomorphs-rules}}\n\n;Options\n*May include up to seven additional Tyranid Warriors --- 14 points/model\n*One model may take an option from the {{Basic Bio-cannons||$:/templates/tooltips}} list. If the unit numbers ten, then two models may take such an option.\n*Any model may take items from the {{Basic Bio-weapons||$:/templates/tooltips}}, {{Biomorphs||$:/templates/tooltips}} and {{Melee Bio-weapons||$:/templates/tooltips}} lists.\n",
        "creator": "Jeanbeaux",
        "modified": "20201012231047193",
        "modifier": "Jeanbeaux",
        "tags": "Troops",
        "type": "text/vnd.tiddlywiki",
        "armor-save": "4+",
        "attacks": "3",
        "ballistics-skill": "3",
        "biomorphs": "[[Two pairs of Scything Talons]]",
        "caption": "Tyranid Warrior Brood",
        "footer": "{{$:/Lore/Tyranid Warriors}}",
        "initiative": "4",
        "leadership": "10",
        "points": " 42",
        "special-rules": "[[Synapse Creature]] [[Shadow in the Warp]] [[Very Bulky]] +[sort[title]]",
        "strength": "4",
        "toughness": "4",
        "unit-type": "Infantry",
        "weapon-skill": "5",
        "wounds": "3"
    }
]